Workbook

Sheet Start here
B1: HCM Academy section audit
B2: Sign up for a section, then audit every course topic in it. V.01 draft.
A4: 1 | B4: Sign up. On the Sign-up tab, put your name and email in Reviewer 1 or Reviewer 2 for a section that still has an open slot (highlighted). Two reviewers per section, at most.
A5: 2 | B5: Set a target date and change Audit status to In progress.
A6: 3 | B6: Open your section's tab (Go to section link). For each course topic, open the course (Link), then fill in the cream columns: your name, a Decision (Keep, Change, Remove, Merge), Merge with (if Merge), whether the steps, job aid, and quiz are accurate, and your notes.
A7: 4 | B7: 'Open items to confirm' lists what we already know needs a Vanderbilt check. Answer those in your notes when you can.
A8: 5 | B8: When every row is done, pick a Section verdict on the Sign-up tab and set Audit status to Done.
B10: Courses marked 'Oracle docs, pending SME review' were built from Oracle documentation and official sources. Check them closely against how Vanderbilt does the work.
B11: Coming soon rows have no course yet. Use Notes to say what the course should cover or who the source should be.
B12: Gray columns are filled in for you. PCB status and PCB response are for the PCB team.
B13: Site: https://me5231979.github.io/HCM_Academy/ · Playbook: https://me5231979.github.io/HCM_Academy/playbook/HCM_Playbook.pdf · Questions: pcb@vanderbilt.edu

Sheet Sign-up
A1: Section | B1: Course topics | C1: Live / coming soon | D1: Est. review time | E1: Reviewer 1 | F1: Reviewer 1 email | G1: Reviewer 2 | H1: Reviewer 2 email | I1: Target date | J1: Audit status | K1: Audited so far | L1: Section verdict | M1: Section notes | N1: Go to section
A2: 00 Start Here: HCM Foundations | B2: 9 | C2: 7 / 2 | D2: about 55 min | J2: Not started | K2: =IFERROR(COUNTA('00 Start Here'!J2:J10)/9,0) | N2: Open tab
A3: 01 Positions, Recruitment & Hiring | B3: 19 | C3: 14 / 5 | D3: about 115 min | J3: Not started | K3: =IFERROR(COUNTA('01 Hiring'!J2:J20)/19,0) | N3: Open tab
A4: 02 Payroll & Timecards | B4: 12 | C4: 12 / 0 | D4: about 110 min | J4: Not started | K4: =IFERROR(COUNTA('02 Payroll'!J2:J13)/12,0) | N4: Open tab
A5: 03 Assignments | B5: 13 | C5: 13 / 0 | D5: about 100 min | J5: Not started | K5: =IFERROR(COUNTA('03 Assignments'!J2:J14)/13,0) | N5: Open tab
A6: 04 Leave Management | B6: 5 | C6: 3 / 2 | D6: about 25 min | J6: Not started | K6: =IFERROR(COUNTA('04 Leave'!J2:J6)/5,0) | N6: Open tab
A7: 05 Costing Management | B7: 5 | C7: 5 / 0 | D7: about 60 min | J7: Not started | K7: =IFERROR(COUNTA('05 Costing'!J2:J6)/5,0) | N7: Open tab
A8: 06 Student & Faculty Hiring and Assignments | B8: 11 | C8: 4 / 7 | D8: about 30 min | J8: Not started | K8: =IFERROR(COUNTA('06 Students and Faculty'!J2:J12)/11,0) | N8: Open tab
A9: 07 Document Records & Reporting | B9: 5 | C9: 5 / 0 | D9: about 45 min | J9: Not started | K9: =IFERROR(COUNTA('07 Records'!J2:J6)/5,0) | N9: Open tab

Sheet 00 Start Here
A1: # | B1: Subtopic | C1: Course topic | D1: Course status | E1: Source | F1: Link | G1: Time | H1: Open items to confirm | I1: Reviewer | J1: Decision | K1: Merge with | L1: Steps accurate? | M1: Job aid OK? | N1: Quiz OK? | O1: Notes or changes needed | P1: Priority | Q1: PCB status | R1: PCB response
A2: 1 | B2: Start Here: HCM Foundations | C2: HCM Structure and Key Concepts | D2: Live | E2: Oracle docs, pending SME review | F2: Open | G2: 6 min | H2: - Confirm which person types and work relationship types Vanderbilt uses and what each one means for pay. - Which person types and work relationship types Vanderbilt uses (Employee, Nonworker, Contingent Worker, Pending Worker) and what each means for pay - Whether 'work unit' is the on-screen label for department at Vanderbilt - Vanderbilt's employment model (single vs. multiple assignments) and legal employer name(s) | Q2: Open
A3: 2 | B3: Start Here: HCM Foundations | C3: HCM Workflow and Worklists | D3: Live | E3: Oracle docs, pending SME review | F3: Open | G3: 5 min | H3: - Confirm Vanderbilt's approval chains by transaction type, whether delegation is enabled for HCMs, and the exact action labels on screen. - Exact action labels on the Redwood notification (Approve, Reject, Request More Information, Withdraw, Resubmit, Send back) - Whether HCMs can withdraw their own transactions and delegate approvals in Vanderbilt's configuration - Vanderbilt approval chains by transaction type | Q3: Open
A4: 3 | B4: Start Here: HCM Foundations | C4: Quick Actions and Viewing Person and Employment Information | D4: Live | E4: Oracle docs, pending SME review | F4: Open | G4: 5 min | H4: - Confirm how HCMs view a record as of a past or future date on the Redwood Employment Info page at Vanderbilt. - How to view a record as of a past or future date on Redwood Employment Info - That Employment Info search accepts person number, and what columns the results show - That clicking a history entry opens View Employment Details in Vanderbilt's release | Q4: Open
A5: 4 | B5: Start Here: HCM Foundations | C5: The Shared Administrative Calendar | D5: Coming soon | E5: No content yet | G5: 10 min | H5: Needs a source: SME session, guide, or recording. | Q5: Open
A6: 5 | B6: Start Here: HCM Foundations | C6: Confidentiality and Secure Access Agreement (annual) | D6: Coming soon | E6: No content yet | G6: 10 min | H6: Needs a source: SME session, guide, or recording. | Q6: Open
A7: 6 | B7: Start Here: HCM Foundations | C7: FERPA Tutorial for Staff | D7: Live | E7: Oracle docs, pending SME review | F7: Open | G7: 6 min | H7: - Confirm Vanderbilt's FERPA office or Registrar contact, the required FERPA training, and how student worker records are classified. - Vanderbilt FERPA office or Registrar contact and required FERPA training for HCMs - How Vanderbilt classifies student worker employment records under FERPA - Vanderbilt's designated directory information categories | Q7: Open
A8: 7 | B8: Start Here: HCM Foundations | C8: I-9 and background check requirements by worker type | D8: Live | E8: Oracle docs, pending SME review | F8: Open | G8: 5 min | H8: - Confirm who completes Section 2 of the I-9 at Vanderbilt, in which system, and how remote hires are handled. - Who completes I-9 Section 2 at Vanderbilt and in which system (and whether E-Verify is used) - How remote hires complete the I-9 - Formstack request link and which populations use it | Q8: Open
A9: 8 | B9: Start Here: HCM Foundations | C9: Employee or independent contractor? | D9: Live | E9: Oracle docs, pending SME review | F9: Open | G9: 6 min | H9: - Confirm Vanderbilt's process and contact for worker classification questions. - Vanderbilt policy on paying students for services (stipend, invoice, gift card) - Who applies the student FICA exception (payroll) | Q9: Open
A10: 9 | B10: Start Here: HCM Foundations | C10: Data integrity: bad data in, bad data out | D10: Live | E10: Oracle docs, pending SME review | F10: Open | G10: 5 min | H10: - Confirm which data errors Vanderbilt sees most often and who to contact for corrections. - Which position attributes Vanderbilt synchronizes to assignments - Most common data errors and the correction contact - Which Departmental Playbook reports HCMs should run before payroll | Q10: Open

Sheet 01 Hiring
A1: # | B1: Subtopic | C1: Course topic | D1: Course status | E1: Source | F1: Link | G1: Time | H1: Open items to confirm | I1: Reviewer | J1: Decision | K1: Merge with | L1: Steps accurate? | M1: Job aid OK? | N1: Quiz OK? | O1: Notes or changes needed | P1: Priority | Q1: PCB status | R1: PCB response
A2: 1 | B2: Position Management | C2: Job Architecture overview and how it impacts recruiting decisions | D2: Live | E2: Vanderbilt SME sources | F2: Open | G2: 4 min | Q2: Open
A3: 2 | B3: Position Management | C3: When to create a new position vs. update an existing position | D3: Live | E3: Vanderbilt SME sources | F3: Open | G3: 4 min | Q3: Open
A4: 3 | B4: Position Management | C4: Create a position | D4: Live | E4: Vanderbilt SME sources | F4: Open | G4: 8 min | H4: - The Workforce Structures > Positions path - The Term/Flex field name and rules - The part-time hours threshold - VTS (Vanderbilt Temporary Services) naming - That a regular HCM (not a super-user) sees Our Workforce and this quick action | Q4: Open
A5: 4 | B5: Position Management | C5: Update a position | D5: Live | E5: Vanderbilt SME sources | F5: Open | G5: 6 min | H5: - The Update action and reason names for a reclassification - Which fields sync from position to assignment - That a regular HCM (not a super-user) sees Our Workforce and this quick action | Q5: Open
A6: 5 | B6: Position Management | C6: Position management best practices | D6: Live | E6: Vanderbilt SME sources | F6: Open | G6: 4 min | H6: - That a regular HCM (not a super-user) sees Our Workforce and this quick action | Q6: Open
A7: 6 | B7: Hiring | C7: Compensation Management: Getting the Compensation Memo | D7: Live | E7: Vanderbilt SME sources | F7: Open | G7: 4 min | H7: - How to submit the Compensation help desk ticket - That a regular HCM (not a super-user) sees Our Workforce and this quick action | Q7: Open
A8: 7 | B8: Hiring | C8: Create a requisition | D8: Live | E8: Vanderbilt SME sources | F8: Open | G8: 9 min | H8: - The Hiring > Requisitions path - The configuration labels for candidate selection process and background check account (VAN000, VAN09) - Cielo billing terms - That a regular HCM (not a super-user) sees Our Workforce and this quick action | Q8: Open
A9: 8 | B9: Hiring | C9: Background checks | D9: Live | E9: Vanderbilt SME sources | F9: Open | G9: 4 min | H9: - The Formstack request for populations not on a requisition - That a regular HCM (not a super-user) sees Our Workforce and this quick action | Q9: Open
A10: 9 | B10: Hiring | C10: Convert a pending worker | D10: Live | E10: Vanderbilt SME sources | F10: Open | G10: 10 min | H10: - The Pending Workers path and section names - The hire reasons - The assignment status labels - The new hire report field - That a regular HCM (not a super-user) sees Our Workforce and this quick action | Q10: Open
A11: 10 | B11: Hiring | C11: Rehires and eligibility for rehire | D11: Live | E11: Oracle docs, pending SME review | F11: Open | G11: 5 min | H11: - Confirm with your engagement consultant (EC) who can approve rehiring someone marked No, and how Not specified is handled. - Exact label of the rehire field on Vanderbilt's Terminate Employment page (Recommended for rehire or Eligible for rehire) and its values (Yes, No, Not specified) - Who can approve rehiring someone marked No, and how Not specified is treated - Where recruiters see the rehire recommendation in Oracle Recruiting - Whether rehires through a requisition need any extra step before conversion | Q11: Open
A12: 11 | B12: Hiring | C12: Staff | D12: Live | E12: Oracle docs, pending SME review | F12: Open | G12: 6 min | H12: - Confirm with your engagement consultant (EC) any lead times between steps your area should plan for. - Course names and links on the landing page match: Get the compensation memo, Create a position, Create a requisition, Background checks, Convert a pending worker, Enter costing for a person - Typical lead times between steps (memo, position approval, requisition approval, background check) - Whether there is an Academy course on the recruiter and offer stage to link | Q12: Open
A13: 12 | B13: Hiring | C13: Interns (Paid and Unpaid) | D13: Live | E13: Oracle docs, pending SME review | F13: Open | G13: 6 min | H13: - Confirm with your engagement consultant (EC) which Oracle worker type and category Vanderbilt uses for paid and unpaid interns, and which checks apply. - Confirm with your EC whether any state where the intern works has stricter internship rules. - Oracle worker type, assignment category, and hire reason Vanderbilt uses for paid interns and unpaid interns - Whether unpaid interns are set up as non-workers or affiliates, and which checks (I-9, background) apply - Who at Vanderbilt approves an unpaid internship against the primary beneficiary test - Any state-specific internship rules for NY, CA, FL, DC | Q13: Open
A14: 13 | B14: Hiring | C14: Union Employees | D14: Coming soon | E14: No content yet | G14: 10 min | H14: Needs a source: SME session, guide, or recording. | Q14: Open
A15: 14 | B15: Hiring | C15: Non-Workers | D15: Live | E15: Vanderbilt SME sources | F15: Open | G15: 3 min | H15: - The non-employment hire reason name - That a regular HCM (not a super-user) sees Our Workforce and this quick action | Q15: Open
A16: 15 | B16: Hiring | C16: Executive or External Search | D16: Live | E16: Vanderbilt SME sources | F16: Open | G16: 3 min | Q16: Open
A17: 16 | B17: Regional and Out-of-State Hiring | C17: Out of State Risk Assessment | D17: Coming soon | E17: No content yet | G17: 10 min | H17: Needs a source: SME session, guide, or recording. | Q17: Open
A18: 17 | B18: Regional and Out-of-State Hiring | C18: Pay transparency | D18: Coming soon | E18: No content yet | G18: 10 min | H18: Needs a source: SME session, guide, or recording. | Q18: Open
A19: 18 | B19: Regional and Out-of-State Hiring | C19: Payroll cadence | D19: Coming soon | E19: No content yet | G19: 10 min | H19: Needs a source: SME session, guide, or recording. | Q19: Open
A20: 19 | B20: Regional and Out-of-State Hiring | C20: Regional benefits and leave | D20: Coming soon | E20: No content yet | G20: 10 min | H20: Needs a source: SME session, guide, or recording. | Q20: Open

Sheet 02 Payroll
A1: # | B1: Subtopic | C1: Course topic | D1: Course status | E1: Source | F1: Link | G1: Time | H1: Open items to confirm | I1: Reviewer | J1: Decision | K1: Merge with | L1: Steps accurate? | M1: Job aid OK? | N1: Quiz OK? | O1: Notes or changes needed | P1: Priority | Q1: PCB status | R1: PCB response
A2: 1 | B2: Payroll & Timecards | C2: The HCM's role in payroll | D2: Live | E2: Vanderbilt SME sources | F2: Open | G2: 5 min | H2: - The exact payroll elements to confirm at hire are still being documented with the payroll team. | Q2: Open
A3: 2 | B3: Payroll & Timecards | C3: Weekly time card check | D3: Live | E3: Vanderbilt SME sources | F3: Open | G3: 6 min | H3: - The pay code names in the Time Off list (PTO-Vacation and sick) - Who to contact when UKG access is missing | Q3: Open
A4: 3 | B4: Payroll & Timecards | C4: Review and approve time cards | D4: Live | E4: Vanderbilt SME sources | F4: Open | G4: 7 min | H4: - The pay code names in the Time Off list (PTO-Vacation and sick) - Who to contact when UKG access is missing | Q4: Open
A5: 4 | B5: Payroll & Timecards | C5: Enter PTO for an employee | D5: Live | E5: Vanderbilt SME sources | F5: Open | G5: 5 min | H5: - The pay code names in the Time Off list (PTO-Vacation and sick) - Who to contact when UKG access is missing | Q5: Open
A6: 5 | B6: Payroll & Timecards | C6: UKG: Timecards, Time Off, and Schedules for Managers | D6: Live | E6: Oracle docs, pending SME review | F6: Open | G6: 6 min | H6: - Confirm the exact manager screens Vanderbilt uses (Manage Timecards, Control Center, schedule views), any delegate approver setup, and the manager approval deadline each pay period. - Exact manager screens at Vanderbilt (Manage Timecards, Control Center, schedule views) and their labels - Whether managers open UKG via Me > Apps > UKG (Kronos) Timesheets like employees - Manager approval deadline each pay period and delegate approver setup - Whether managers can mark exceptions reviewed or must correct punches | Q6: Open
A7: 6 | B7: Payroll & Timecards | C7: UKG: Employee Timecards and Time Off | D7: Live | E7: Oracle docs, pending SME review | F7: Open | G7: 6 min | H7: - Confirm whether Vanderbilt employees punch at clocks, use web or mobile punch, or enter hours on a timesheet, and which accrual balances display. - How Vanderbilt employees record time (clock punch, web/mobile punch, or timesheet entry) - Which accrual balances employees see and where - Screenshot of + row and Browse in the Time Off column with PTO-Vacation | Q7: Open
A8: 7 | B8: Payroll & Timecards | C8: Request an off-cycle payment | D8: Live | E8: Vanderbilt SME sources | F8: Open | G8: 6 min | H8: - The off-cycle request form link and its current criteria - That a regular HCM (not a super-user) sees Our Workforce and this quick action | Q8: Open
A9: 8 | B9: Compensation Management | C9: Change salary | D9: Live | E9: Vanderbilt SME sources | F9: Open | G9: 8 min | H9: - The Change Salary section names - The reason list values - The amount and percentage field labels - That a regular HCM (not a super-user) sees Our Workforce and this quick action | Q9: Open
A10: 9 | B10: Compensation Management | C10: Process grossed-up additional compensation | D10: Live | E10: Vanderbilt SME sources | F10: Open | G10: 6 min | H10: - The Individual Compensation quick action name - Plan names (Lump sum payment, Bonus, staff supplements) - The Net, Amount, Process separately, and Ongoing field labels - That a regular HCM (not a super-user) sees Our Workforce and this quick action | Q10: Open
A11: 10 | B11: Compensation Management | C11: Add a one-time payment (such as a sign-on bonus) | D11: Live | E11: Vanderbilt SME sources | F11: Open | G11: 6 min | H11: - The Individual Compensation quick action name - Plan names (Lump sum payment, Bonus, staff supplements) - The Net, Amount, Process separately, and Ongoing field labels - That a regular HCM (not a super-user) sees Our Workforce and this quick action | Q11: Open
A12: 11 | B12: Compensation Management | C12: Add a staff supplement | D12: Live | E12: Vanderbilt SME sources | F12: Open | G12: 7 min | H12: - The Individual Compensation quick action name - Plan names (Lump sum payment, Bonus, staff supplements) - The Net, Amount, Process separately, and Ongoing field labels - That a regular HCM (not a super-user) sees Our Workforce and this quick action | Q12: Open
A13: 12 | B13: Compensation Management | C13: Compensation impacts on payroll processing | D13: Live | E13: Oracle docs, pending SME review | F13: Open | G13: 7 min | H13: - Confirm with payroll which Vanderbilt earnings use Process separately and how retro shows on the payslip. - Payroll confirms retro behavior and how retro lines appear on the payslip - Which Vanderbilt earnings are set to Process separately or pay separately - Vanderbilt action name and path for salary changes under Our Workforce > Quick Actions - Biweekly/weekly cutoff relative to UKG approval deadlines | Q13: Open

Sheet 03 Assignments
A1: # | B1: Subtopic | C1: Course topic | D1: Course status | E1: Source | F1: Link | G1: Time | H1: Open items to confirm | I1: Reviewer | J1: Decision | K1: Merge with | L1: Steps accurate? | M1: Job aid OK? | N1: Quiz OK? | O1: Notes or changes needed | P1: Priority | Q1: PCB status | R1: PCB response
A2: 1 | B2: Assignment Changes | C2: Change Assignment | D2: Live | E2: Vanderbilt SME sources | F2: Open | G2: 6 min | H2: - The Employment Info path - The action and reason names - That a regular HCM (not a super-user) sees Our Workforce and this quick action | Q2: Open
A3: 2 | B3: Assignment Changes | C3: Add Assignment | D3: Live | E3: Oracle docs, pending SME review | F3: Open | G3: 5 min | H3: - Confirm Vanderbilt's action reasons for an added assignment and whether a second assignment needs a pre-approval from Compensation or your PCB consultant. - Add Assignment appears under Our Workforce > Quick Actions (Show More) in Vanderbilt's Redwood pages - Vanderbilt action reasons to use for an added assignment - Whether a second assignment needs Compensation or PCB consultant approval - Exact label and location of the primary assignment flag on the Assignment step | Q3: Open
A4: 3 | B4: Assignment Changes | C4: Change Working Hours | D4: Live | E4: Vanderbilt SME sources | F4: Open | G4: 4 min | H4: - The reason name for a change in working hours - That a regular HCM (not a super-user) sees Our Workforce and this quick action | Q4: Open
A5: 4 | B5: Assignment Changes | C5: Direct Reports | D5: Live | E5: Oracle docs, pending SME review | F5: Open | G5: 4 min | H5: - Confirm whether a new manager needs a manager role or UKG approver setup at Vanderbilt; Oracle notes the Direct Reports task does not grant manager roles. - Direct Reports action is available from Employment Info for HCMs (vs. only My Team) - Whether a new manager needs a manager role or UKG approver setup, and who requests it - Whether Vanderbilt's Redwood Direct Reports page is enabled (profile ORA_PER_EMPL_MNG_DIR_REDWOOD_ENABLED) | Q5: Open
A6: 5 | B6: Assignment Changes | C6: Promote | D6: Live | E6: Oracle docs, pending SME review | F6: Open | G6: 6 min | H6: - Confirm Vanderbilt's promotion action reasons and any Compensation approval needed for the new salary. - Promote and Promote and Change Position both appear in Our Workforce > Quick Actions for HCMs - Vanderbilt promotion action reasons - Whether a promotion salary needs Compensation approval or a memo - Whether HCMs are expected to use Promote and Change Position or request position changes separately | Q6: Open
A7: 6 | B7: Transfers and Promotions | C7: Transfer or promotion from a requisition | D7: Live | E7: Vanderbilt SME sources | F7: Open | G7: 3 min | Q7: Open
A8: 7 | B8: Transfers and Promotions | C8: Transfer or promotion without a requisition | D8: Live | E8: Vanderbilt SME sources | F8: Open | G8: 5 min | H8: - The 5-business-day internal posting rule for internal moves is a separate initiative. - The transfer type names (organization transfer, transfer to faculty status) - That a regular HCM (not a super-user) sees Our Workforce and this quick action | Q8: Open
A9: 8 | B9: Offboarding | C9: Voluntary termination | D9: Live | E9: Vanderbilt SME sources | F9: Open | G9: 7 min | H9: - The seniority dates screen is no longer editable since Redwood. Skip it for now. - The Terminate Employment section names - The revoke access, rehire, and payroll eligibility field labels - Whether the seniority dates screen still appears - That a regular HCM (not a super-user) sees Our Workforce and this quick action | Q9: Open
A10: 9 | B10: Offboarding | C10: Reduction in force (RIF) | D10: Live | E10: Vanderbilt SME sources | F10: Open | G10: 7 min | H10: - The Terminate Employment section names - The revoke access, rehire, and payroll eligibility field labels - Whether the seniority dates screen still appears - That a regular HCM (not a super-user) sees Our Workforce and this quick action | Q10: Open
A11: 10 | B11: Offboarding | C11: Involuntary termination (misconduct) | D11: Live | E11: Vanderbilt SME sources | F11: Open | G11: 6 min | H11: - Confirm the exact name of the rehire eligibility field in Vanderbilt's Oracle. - The Terminate Employment section names - The revoke access, rehire, and payroll eligibility field labels - Whether the seniority dates screen still appears - The exact rehire eligibility field name - That a regular HCM (not a super-user) sees Our Workforce and this quick action | Q11: Open
A12: 11 | B12: Offboarding | C12: Ending assignments vs. terminating employment | D12: Live | E12: Oracle docs, pending SME review | F12: Open | G12: 4 min | H12: - Confirm which End Assignment entry point Vanderbilt uses (Change Assignment > End Assignment or the termination page), since it depends on the termination version configured. - Which termination version Vanderbilt uses and where End Assignment lives (Change Assignment > End Assignment or the termination page) - Whether the cited facuk guide page matches US behavior (it is from a localized guide) | Q12: Open
A13: 12 | B13: Offboarding | C13: How to handle a termination when an employee has multiple assignments | D13: Live | E13: Oracle docs, pending SME review | F13: Open | G13: 5 min | H13: - Confirm Vanderbilt's rule for who submits when the jobs sit in different business units. - Who submits when the assignments are in different business units - Whether the primary flag change can be made in the same transaction as End Assignment | Q13: Open
A14: 13 | B14: Offboarding | C14: Offboarding process requirements | D14: Live | E14: Oracle docs, pending SME review | F14: Open | G14: 6 min | H14: - Confirm Vanderbilt's process and owners for equipment return, the exit survey, and final timecard approval for non-exempt employees. - Owner and process for equipment return - Whether Vanderbilt has an exit survey and who sends it - Final timecard approval steps and deadline for non-exempt leavers - Whether HCMs must end costing manually or it ends with the assignment - Which Document Records types are expected at offboarding | Q14: Open

Sheet 04 Leave
A1: # | B1: Subtopic | C1: Course topic | D1: Course status | E1: Source | F1: Link | G1: Time | H1: Open items to confirm | I1: Reviewer | J1: Decision | K1: Merge with | L1: Steps accurate? | M1: Job aid OK? | N1: Quiz OK? | O1: Notes or changes needed | P1: Priority | Q1: PCB status | R1: PCB response
A2: 1 | B2: Leave Management | C2: Leave status updates | D2: Coming soon | E2: No content yet | G2: 10 min | H2: Needs a source: SME session, guide, or recording. | Q2: Open
A3: 2 | B3: Leave Management | C3: Entering and managing FMLA/TMLA transactions (continuous vs. intermittent) | D3: Live | E3: Oracle docs, pending SME review | F3: Open | G3: 7 min | H3: - Which Oracle absence types Vanderbilt uses for FMLA, TMLA (TPLA), and FMLA running at the same time as state leave, and who enters intermittent occurrences, must be confirmed. - Vanderbilt's leave process is pending review by the Leave SME. - Oracle absence types Vanderbilt uses for FMLA, TMLA/TPLA, and concurrent FMLA and state leave - Who enters intermittent occurrences (HCM, employee, or Leave team) and how often - Whether FMLA is tracked in hours or days at Vanderbilt and which 12-month period method is used - Current TPLA eligibility rules and leave length in T.C.A. 4-21-408 (confirm with Leave SME or legal) - Whether a continuous FMLA/TMLA leave also requires a leave status change in Change Assignment - The Leave SME (Leave SME) review of the full FMLA/TMLA process | Q3: Open
A4: 3 | B4: Leave Management | C4: Differences in processing leaves for monthly vs. biweekly employees | D4: Coming soon | E4: No content yet | G4: 10 min | H4: Needs a source: SME session, guide, or recording. | Q4: Open
A5: 4 | B5: Leave Management | C5: Leave administration workflows within Oracle | D5: Live | E5: Oracle docs, pending SME review | F5: Open | G5: 6 min | H5: - Vanderbilt's approval routing for each absence type (who approves, whether HR or the Leave team is in the chain, what happens if an approver does not act) must be confirmed. - Vanderbilt's leave process is pending review by the Leave SME. - Approval routing for each Vanderbilt absence type (approvers, Leave team involvement) - Whether absence approvals expire or escalate, and the action on expiry - Whether HCMs can see and act on requests for their area in the notifications bell - Whether withdrawals of approved absences require approval at Vanderbilt - The Leave SME (Leave SME) review of the full workflow | Q5: Open
A6: 5 | B6: Leave Management | C6: Managing Exempt Time Off in Oracle | D6: Live | E6: Oracle docs, pending SME review | F6: Open | G6: 5 min | H6: - Which quick actions HCMs see under Our Workforce, and whether HCMs approve exempt time off or only managers do, must be confirmed on screen. - Vanderbilt's leave process is pending review by the Leave SME. - Which absence quick actions (Add Absence, Existing Absences, Absence Balance) HCMs see under Our Workforce > Quick Actions - Absence types and plans available to exempt employees (vacation, sick, etc.) - Whether exempt time off can be entered in partial days or hours - The Leave SME (Leave SME) review of the full process | Q6: Open

Sheet 05 Costing
A1: # | B1: Subtopic | C1: Course topic | D1: Course status | E1: Source | F1: Link | G1: Time | H1: Open items to confirm | I1: Reviewer | J1: Decision | K1: Merge with | L1: Steps accurate? | M1: Job aid OK? | N1: Quiz OK? | O1: Notes or changes needed | P1: Priority | Q1: PCB status | R1: PCB response
A2: 1 | B2: Costing Management | C2: Costing fundamentals | D2: Live | E2: Vanderbilt SME sources | F2: Open | G2: 7 min | H2: - Where Costing for Persons sits in Redwood - The Advanced Search and Effective As-of Date labels - The Actions and Edit menu labels - That a regular HCM (not a super-user) sees Our Workforce and this quick action | Q2: Open
A3: 2 | B3: Costing Management | C3: How employee costing impacts payroll and financial reporting | D3: Live | E3: Oracle docs, pending SME review | F3: Open | G3: 6 min | H3: - Confirm how Vanderbilt handles grant labor distribution and the deadline to fix costing before a payroll run. - Where Costing for Persons sits in Vanderbilt navigation - How Vanderbilt distributes grant labor costs (labor schedules or payroll costing) - Deadline to correct costing before a payroll run and who runs cost adjustments or retroactive costing | Q3: Open
A4: 3 | B4: Costing Management | C4: When costing must be updated | D4: Live | E4: Vanderbilt SME sources | F4: Open | G4: 6 min | H4: - Where Costing for Persons sits in Redwood - The Advanced Search and Effective As-of Date labels - The Actions and Edit menu labels - That a regular HCM (not a super-user) sees Our Workforce and this quick action | Q4: Open
A5: 4 | B5: Costing Management | C5: Enter costing for a person | D5: Live | E5: Vanderbilt SME sources | F5: Open | G5: 10 min | H5: - Where Costing for Persons sits in Redwood - The Advanced Search and Effective As-of Date labels - The Actions and Edit menu labels - That a regular HCM (not a super-user) sees Our Workforce and this quick action | Q5: Open
A6: 5 | B6: Costing Management | C6: Change existing costing | D6: Live | E6: Vanderbilt SME sources | F6: Open | G6: 10 min | H6: - Where Costing for Persons sits in Redwood - The Advanced Search and Effective As-of Date labels - The Actions and Edit menu labels - That a regular HCM (not a super-user) sees Our Workforce and this quick action | Q6: Open

Sheet 06 Students and Faculty
A1: # | B1: Subtopic | C1: Course topic | D1: Course status | E1: Source | F1: Link | G1: Time | H1: Open items to confirm | I1: Reviewer | J1: Decision | K1: Merge with | L1: Steps accurate? | M1: Job aid OK? | N1: Quiz OK? | O1: Notes or changes needed | P1: Priority | Q1: PCB status | R1: PCB response
A2: 1 | B2: Students | C2: Student hiring process and requirements | D2: Live | E2: Oracle docs, pending SME review | F2: Open | G2: 5 min | H2: - Vanderbilt owner for student eligibility (enrollment, hour limits, international student work authorization) is not yet documented. Confirm with your PCB consultant. - Whether student hires come through Oracle Recruiting requisitions or a direct hire in your area. - Who confirms student eligibility (enrollment, hour limits, work authorization for international students). - Whether student hires come through ORC requisitions, pending worker conversion, or a direct add in Our Workforce. - Exact Vanderbilt names of the three student setups as they appear in Oracle. | Q2: Open
A3: 2 | B3: Students | C3: Student Workers | D3: Live | E3: Oracle docs, pending SME review | F3: Open | G3: 6 min | H3: - Vanderbilt rules on student hour limits, eligibility checks, and who confirms enrollment are not yet documented. - Exact Quick Action names for adding a Work Relationship and adding an assignment in Our Workforce. - Student hour limits and end-date rules (term end vs academic year). - Who decides FLSA status for graduate teaching or research assistants (Compensation?). - That student pay elements cost to 5130 by default. | Q3: Open
A4: 3 | B4: Students | C4: Student Expense Only | D4: Coming soon | E4: No content yet | G4: 10 min | H4: Needs a source: SME session, guide, or recording. | Q4: Open
A5: 4 | B5: Students | C5: Service Free Stipend | D5: Coming soon | E5: No content yet | G5: 10 min | H5: Needs a source: SME session, guide, or recording. | Q5: Open
A6: 5 | B6: Students | C6: Add a Work Relationship or add an Assignment? | D6: Live | E6: Oracle docs, pending SME review | F6: Open | G6: 4 min | H6: - Confirm the exact Quick Action names Vanderbilt uses for these two actions in Our Workforce. - That the enrolled student (N) record is an Oracle nonworker work relationship and what creates it. - Exact Quick Action names and whether Add Assignment is enabled for HCMs. | Q6: Open
A7: 6 | B7: Faculty | C7: Faculty hiring process and requirements | D7: Coming soon | E7: No content yet | G7: 10 min | H7: Needs a source: SME session, guide, or recording. | Q7: Open
A8: 7 | B8: Faculty | C8: Faculty | D8: Coming soon | E8: No content yet | G8: 10 min | H8: Needs a source: SME session, guide, or recording. | Q8: Open
A9: 8 | B9: Faculty | C9: Emeritus | D9: Coming soon | E9: No content yet | G9: 10 min | H9: Needs a source: SME session, guide, or recording. | Q9: Open
A10: 9 | B10: Faculty | C10: FERDC | D10: Coming soon | E10: No content yet | G10: 10 min | H10: Needs a source: SME session, guide, or recording. | Q10: Open
A11: 10 | B11: Changes and Approvals | C11: Student and faculty assignment changes | D11: Live | E11: Oracle docs, pending SME review | F11: Open | G11: 6 min | H11: - Vanderbilt's term-change calendar and whether student assignments are ended or extended in bulk. - That End Assignment appears in the Vanderbilt Redwood Change Assignment When and why step. | Q11: Open
A12: 11 | B12: Changes and Approvals | C12: Oracle transactions and approvals for these populations | D12: Coming soon | E12: No content yet | G12: 10 min | H12: Needs a source: SME session, guide, or recording. | Q12: Open

Sheet 07 Records
A1: # | B1: Subtopic | C1: Course topic | D1: Course status | E1: Source | F1: Link | G1: Time | H1: Open items to confirm | I1: Reviewer | J1: Decision | K1: Merge with | L1: Steps accurate? | M1: Job aid OK? | N1: Quiz OK? | O1: Notes or changes needed | P1: Priority | Q1: PCB status | R1: PCB response
A2: 1 | B2: Document Records & Reporting | C2: Add a document record | D2: Live | E2: Vanderbilt SME sources | F2: Open | G2: 7 min | H2: - The Document Records menu path - The Add button and attachment control labels - That a regular HCM (not a super-user) sees Our Workforce and this quick action | Q2: Open
A3: 2 | B3: Document Records & Reporting | C3: Introduction to BI Reporting and the Departmental Playbook | D3: Live | E3: Oracle docs, pending SME review | F3: Open | G3: 5 min | H3: - Confirm where the Departmental Playbook lives in the catalog (folder path) and whether Vanderbilt exposes Reports and Analytics on a different menu. - Catalog folder path for the Departmental Playbook - Whether Reports and Analytics is reached via Navigator > Tools or another Vanderbilt menu - Full list of Departmental Playbook reports beyond the three costing reports | Q3: Open
A4: 3 | B4: Document Records & Reporting | C4: Reporting 101 | D4: Live | E4: Oracle docs, pending SME review | F4: Open | G4: 5 min | H4: - Confirm which standard HCM reports Vanderbilt expects HCMs to run and where they are stored. - Which standard HCM reports HCMs are expected to run and their folder - Whether those reports use an as-of/effective date prompt | Q4: Open
A5: 4 | B5: Document Records & Reporting | C5: Reporting 201 | D5: Live | E5: Oracle docs, pending SME review | F5: Open | G5: 6 min | H5: - Confirm Vanderbilt rules for storing and emailing exported HR data and whether agents are enabled for HCMs. - Whether HCMs can create agents (More > Schedule) in Vanderbilt's OTBI - Vanderbilt policy for storing and emailing exported HR data | Q5: Open
A6: 5 | B6: Document Records & Reporting | C6: Reporting 301 | D6: Live | E6: Oracle docs, pending SME review | F6: Open | G6: 8 min | H6: - Confirm which BI roles HCMs have, who can publish to Shared Folders > Custom, and the request process for new shared reports. - Whether HCMs hold a BI author role (Create > Analysis visible) - Who can publish to Shared Folders > Custom and the request process - Recommended subject areas for common HCM questions | Q6: Open

Sheet Summary
A1: Section | B1: Reviewers | C1: Course topics | D1: Audited | E1: % done | F1: Keep | G1: Change | H1: Remove | I1: Merge | J1: High priority | K1: Audit status
A2: 00 Start Here: HCM Foundations | B2: =TRIM('Sign-up'!E2&IF(LEN('Sign-up'!G2)>0,", "&'Sign-up'!G2,"")) | C2: 9 | D2: =COUNTA('00 Start Here'!J2:J10) | E2: =IFERROR(D2/C2,0) | F2: =COUNTIF('00 Start Here'!J2:J10,"Keep") | G2: =COUNTIF('00 Start Here'!J2:J10,"Change") | H2: =COUNTIF('00 Start Here'!J2:J10,"Remove") | I2: =COUNTIF('00 Start Here'!J2:J10,"Merge") | J2: =COUNTIF('00 Start Here'!P2:P10,"High") | K2: ='Sign-up'!J2
A3: 01 Positions, Recruitment & Hiring | B3: =TRIM('Sign-up'!E3&IF(LEN('Sign-up'!G3)>0,", "&'Sign-up'!G3,"")) | C3: 19 | D3: =COUNTA('01 Hiring'!J2:J20) | E3: =IFERROR(D3/C3,0) | F3: =COUNTIF('01 Hiring'!J2:J20,"Keep") | G3: =COUNTIF('01 Hiring'!J2:J20,"Change") | H3: =COUNTIF('01 Hiring'!J2:J20,"Remove") | I3: =COUNTIF('01 Hiring'!J2:J20,"Merge") | J3: =COUNTIF('01 Hiring'!P2:P20,"High") | K3: ='Sign-up'!J3
A4: 02 Payroll & Timecards | B4: =TRIM('Sign-up'!E4&IF(LEN('Sign-up'!G4)>0,", "&'Sign-up'!G4,"")) | C4: 12 | D4: =COUNTA('02 Payroll'!J2:J13) | E4: =IFERROR(D4/C4,0) | F4: =COUNTIF('02 Payroll'!J2:J13,"Keep") | G4: =COUNTIF('02 Payroll'!J2:J13,"Change") | H4: =COUNTIF('02 Payroll'!J2:J13,"Remove") | I4: =COUNTIF('02 Payroll'!J2:J13,"Merge") | J4: =COUNTIF('02 Payroll'!P2:P13,"High") | K4: ='Sign-up'!J4
A5: 03 Assignments | B5: =TRIM('Sign-up'!E5&IF(LEN('Sign-up'!G5)>0,", "&'Sign-up'!G5,"")) | C5: 13 | D5: =COUNTA('03 Assignments'!J2:J14) | E5: =IFERROR(D5/C5,0) | F5: =COUNTIF('03 Assignments'!J2:J14,"Keep") | G5: =COUNTIF('03 Assignments'!J2:J14,"Change") | H5: =COUNTIF('03 Assignments'!J2:J14,"Remove") | I5: =COUNTIF('03 Assignments'!J2:J14,"Merge") | J5: =COUNTIF('03 Assignments'!P2:P14,"High") | K5: ='Sign-up'!J5
A6: 04 Leave Management | B6: =TRIM('Sign-up'!E6&IF(LEN('Sign-up'!G6)>0,", "&'Sign-up'!G6,"")) | C6: 5 | D6: =COUNTA('04 Leave'!J2:J6) | E6: =IFERROR(D6/C6,0) | F6: =COUNTIF('04 Leave'!J2:J6,"Keep") | G6: =COUNTIF('04 Leave'!J2:J6,"Change") | H6: =COUNTIF('04 Leave'!J2:J6,"Remove") | I6: =COUNTIF('04 Leave'!J2:J6,"Merge") | J6: =COUNTIF('04 Leave'!P2:P6,"High") | K6: ='Sign-up'!J6
A7: 05 Costing Management | B7: =TRIM('Sign-up'!E7&IF(LEN('Sign-up'!G7)>0,", "&'Sign-up'!G7,"")) | C7: 5 | D7: =COUNTA('05 Costing'!J2:J6) | E7: =IFERROR(D7/C7,0) | F7: =COUNTIF('05 Costing'!J2:J6,"Keep") | G7: =COUNTIF('05 Costing'!J2:J6,"Change") | H7: =COUNTIF('05 Costing'!J2:J6,"Remove") | I7: =COUNTIF('05 Costing'!J2:J6,"Merge") | J7: =COUNTIF('05 Costing'!P2:P6,"High") | K7: ='Sign-up'!J7
A8: 06 Student & Faculty Hiring and Assignments | B8: =TRIM('Sign-up'!E8&IF(LEN('Sign-up'!G8)>0,", "&'Sign-up'!G8,"")) | C8: 11 | D8: =COUNTA('06 Students and Faculty'!J2:J12) | E8: =IFERROR(D8/C8,0) | F8: =COUNTIF('06 Students and Faculty'!J2:J12,"Keep") | G8: =COUNTIF('06 Students and Faculty'!J2:J12,"Change") | H8: =COUNTIF('06 Students and Faculty'!J2:J12,"Remove") | I8: =COUNTIF('06 Students and Faculty'!J2:J12,"Merge") | J8: =COUNTIF('06 Students and Faculty'!P2:P12,"High") | K8: ='Sign-up'!J8
A9: 07 Document Records & Reporting | B9: =TRIM('Sign-up'!E9&IF(LEN('Sign-up'!G9)>0,", "&'Sign-up'!G9,"")) | C9: 5 | D9: =COUNTA('07 Records'!J2:J6) | E9: =IFERROR(D9/C9,0) | F9: =COUNTIF('07 Records'!J2:J6,"Keep") | G9: =COUNTIF('07 Records'!J2:J6,"Change") | H9: =COUNTIF('07 Records'!J2:J6,"Remove") | I9: =COUNTIF('07 Records'!J2:J6,"Merge") | J9: =COUNTIF('07 Records'!P2:P6,"High") | K9: ='Sign-up'!J9
A10: All sections | C10: =SUM(C2:C9) | D10: =SUM(D2:D9) | E10: =IFERROR(D10/C10,0) | F10: =SUM(F2:F9) | G10: =SUM(G2:G9) | H10: =SUM(H2:H9) | I10: =SUM(I2:I9) | J10: =SUM(J2:J9)

Sheet Lists
A1: Keep | B1: Accurate | C1: High | D1: Open | E1: Not started | F1: Right as is
A2: Change | B2: Needs change | C2: Medium | D2: In progress | E2: In progress | F2: Rename
A3: Remove | B3: Wrong | C3: Low | D3: Done | E3: Done | F3: Reorder
A4: Merge | B4: Not reviewed | D4: Won't change | F4: Missing subtopics
F5: Split
F6: Merge with another section
